aiok8s/__init__.py
aiok8s/api/__init__.py
aiok8s/api/meta.py
aiok8s/cache/__init__.py
aiok8s/cache/controller.py
aiok8s/cache/delta_fifo.py
aiok8s/cache/fake_custom_store.py
aiok8s/cache/fifo.py
aiok8s/cache/index.py
aiok8s/cache/list_watch.py
aiok8s/cache/reflector.py
aiok8s/cache/shared_informer.py
aiok8s/cache/store.py
aiok8s/cache/test_controller.py
aiok8s/cache/test_delta_fifo.py
aiok8s/cache/test_fifo.py
aiok8s/cache/test_index.py
aiok8s/cache/test_reflector.py
aiok8s/cache/test_shared_informer.py
aiok8s/cache/test_store.py
aiok8s/cache/thread_safe_store.py
aiok8s/cache/testing/__init__.py
aiok8s/cache/testing/fake_controller_source.py
aiok8s/cache/testing/test_fake_controller_source.py
aiok8s/cache/testing/util.py
aiok8s/controller/__init__.py
aiok8s/controller/_cache_reader.py
aiok8s/controller/_deleg_map.py
aiok8s/controller/_informers_map.py
aiok8s/controller/builder.py
aiok8s/controller/cache.py
aiok8s/controller/controller.py
aiok8s/controller/event.py
aiok8s/controller/handler.py
aiok8s/controller/manager.py
aiok8s/controller/reconcile.py
aiok8s/controller/source.py
aiok8s/leaderelection/__init__.py
aiok8s/leaderelection/leaderelection.py
aiok8s/leaderelection/resourcelock.py
aiok8s/runtime/__init__.py
aiok8s/runtime/schema.py
aiok8s/util/__init__.py
aiok8s/util/_time.py
aiok8s/util/clock.py
aiok8s/util/retry.py
aiok8s/util/test_clock.py
aiok8s/util/test_wait.py
aiok8s/util/wait.py
aiok8s/watch/__init__.py
aiok8s/watch/mux.py
aiok8s/watch/test_mux.py
aiok8s/watch/test_watch.py
aiok8s/watch/watch.py
aiok8s/workqueue/__init__.py
aiok8s/workqueue/default_rate_limiters.py
aiok8s/workqueue/delaying_queue.py
aiok8s/workqueue/queue.py
aiok8s/workqueue/rate_limiting_queue.py
aiok8s/workqueue/test_default_rate_limiters.py
aiok8s/workqueue/test_delaying_queue.py
aiok8s/workqueue/test_queue.py
aiok8s/workqueue/test_rate_limiting_queue.py
aiok8s-0.0.2.dist-info/LICENSE
aiok8s-0.0.2.dist-info/METADATA
aiok8s-0.0.2.dist-info/WHEEL
aiok8s-0.0.2.dist-info/top_level.txt
aiok8s-0.0.2.dist-info/RECORD
