Metadata-Version: 2.1
Name: aiok8s
Version: 0.0.2
Summary: asyncio client tools for Kubernetes
Home-page: https://github.com/tbarrella/aiok8s
Author: Taylor Barrella
Author-email: tbarrella@gmail.com
License: UNKNOWN
Platform: UNKNOWN
Classifier: Development Status :: 2 - Pre-Alpha
Classifier: Intended Audience :: Developers
Classifier: License :: OSI Approved :: Apache Software License
Classifier: Operating System :: OS Independent
Classifier: Programming Language :: Python
Classifier: Programming Language :: Python :: 3
Classifier: Programming Language :: Python :: 3.6
Classifier: Programming Language :: Python :: 3.7
Classifier: Programming Language :: Python :: 3.8
Requires-Python: >=3.6
